imxInsights/__init__.py
imxInsights/py.typed
imxInsights/compare/__init__.py
imxInsights/compare/changeStatusEnum.py
imxInsights/compare/changedImxObject.py
imxInsights/compare/changes.py
imxInsights/compare/geometryChange.py
imxInsights/compare/imxContainerCompare.py
imxInsights/compare/imxContainerCompareChain.py
imxInsights/compare/custom_operators/__init__.py
imxInsights/compare/custom_operators/diff_refs.py
imxInsights/compare/custom_operators/diff_shapely.py
imxInsights/domain/__init__.py
imxInsights/domain/areas.py
imxInsights/domain/imxEnums.py
imxInsights/domain/imxGeographicLocation.py
imxInsights/domain/imxObject.py
imxInsights/domain/imxReferenceObjects.py
imxInsights/exceptions/__init__.py
imxInsights/exceptions/customException.py
imxInsights/exceptions/exceptionHandler.py
imxInsights/exceptions/exceptionLevels.py
imxInsights/exceptions/imxExceptions.py
imxInsights/file/__init__.py
imxInsights/file/imxFile.py
imxInsights/file/xmlFile.py
imxInsights/file/containerizedImx/__init__.py
imxInsights/file/containerizedImx/imxContainer.py
imxInsights/file/containerizedImx/imxContainerFile.py
imxInsights/file/containerizedImx/imxContainerFileReference.py
imxInsights/file/containerizedImx/imxContainerFiles.py
imxInsights/file/containerizedImx/imxContainerMetadata.py
imxInsights/file/containerizedImx/imxContainerProtocol.py
imxInsights/file/containerizedImx/imxDesignCoreFile.py
imxInsights/file/containerizedImx/imxDesignPetalFile.py
imxInsights/file/singleFileImx/__init__.py
imxInsights/file/singleFileImx/imxSingleFile.py
imxInsights/file/singleFileImx/imxSingleFileMetadata.py
imxInsights/file/singleFileImx/imxSituation.py
imxInsights/file/singleFileImx/imxSituationEnum.py
imxInsights/file/singleFileImx/imxSituationProtocol.py
imxInsights/repo/__init__.py
imxInsights/repo/config.py
imxInsights/repo/imxMultiRepo.py
imxInsights/repo/imxMultiRepoObject.py
imxInsights/repo/imxMultiRepoProtocol.py
imxInsights/repo/imxObjectTree.py
imxInsights/repo/imxRepo.py
imxinsights-0.2.2a8.dist-info/METADATA
imxinsights-0.2.2a8.dist-info/WHEEL
imxinsights-0.2.2a8.dist-info/licenses/LICENSE
imxinsights-0.2.2a8.dist-info/RECORD
