Metadata-Version: 2.4
Name: imxInsights
Version: 0.2.2a8
Summary: python imx insights module to get information from imx files
Project-URL: Documentation, https://open-imx.github.io/imxInsights/
Project-URL: Source, https://github.com/open-imx/imxInsights
Author-email: Hzd <Hazedd@users.noreply.github.com>, Open-Imx <open-imx@organisation.noreply.github.com>
License-File: LICENSE
Classifier: Development Status :: 3 - Alpha
Classifier: Intended Audience :: End Users/Desktop
Classifier: License :: OSI Approved :: MIT License
Classifier: Programming Language :: Python :: 3.10
Classifier: Programming Language :: Python :: 3.11
Classifier: Programming Language :: Python :: 3.12
Classifier: Programming Language :: Python :: 3.13
Requires-Python: >=3.10
Requires-Dist: content-types
Requires-Dist: dateparser
Requires-Dist: deepdiff
Requires-Dist: geojson
Requires-Dist: jinja2
Requires-Dist: loguru
Requires-Dist: lxml
Requires-Dist: networkx
Requires-Dist: openpyxl
Requires-Dist: packaging
Requires-Dist: pandas
Requires-Dist: pandas-stubs
Requires-Dist: pyproj
Requires-Dist: shapely
Requires-Dist: tqdm
Requires-Dist: tqdm-stubs
Requires-Dist: types-dateparser
Requires-Dist: types-lxml
Requires-Dist: types-networkx
Requires-Dist: types-openpyxl
Requires-Dist: types-shapely
Requires-Dist: xlsxwriter
